LICENSE
README.md
setup.py
Pytoolsproject/__init__.py
Pytoolsproject/github_api.py
Pytoolsproject.egg-info/PKG-INFO
Pytoolsproject.egg-info/SOURCES.txt
Pytoolsproject.egg-info/dependency_links.txt
Pytoolsproject.egg-info/not-zip-safe
Pytoolsproject.egg-info/requires.txt
Pytoolsproject.egg-info/top_level.txt