Metadata-Version: 2.1
Name: Pytoolsproject
Version: 0.3
Summary: Pytools project: repositório criado para curso pytools.
Home-page: https://github.com/Tiago1Figueira/Pytoolsproject
Author: Tiago figueira
Author-email: tiago_figueira@hotmail.com
License:                     GNU AFFERO GENERAL PUBLIC LICENSE
Platform: UNKNOWN
Classifier: Development Status :: 2 - Pre-Alpha
Classifier: Environment :: Console
Classifier: Intended Audience :: Developers
Classifier: License :: OSI Approved :: GNU Lesser General Public License v3 or later (LGPLv3+)
Classifier: Operating System :: OS Independent
Classifier: Programming Language :: Python
Classifier: Programming Language :: Python :: 3.9
Classifier: Framework :: Pytest
License-File: LICENSE
